{
    "info": {
        "_postman_id": "8b5f3a1e-8e4d-4b8a-9f5c-2e6b7c8d9e0f",
        "name": "Najax POS API",
        "description": "Comprehensive API collection for testing Najax POS authentication, business management, and user features.",
        "schema": "https://schema.getpostman.com/json/collection/v2.1.0/collection.json"
    },
    "item": [
        {
            "name": "Authentication",
            "item": [
                {
                    "name": "Sign Up",
                    "request": {
                        "method": "POST",
                        "header": [],
                        "body": {
                            "mode": "raw",
                            "raw": "{\n  \"email\": \"user@example.com\",\n  \"password\": \"SecurePassword123!\",\n  \"name\": \"John Doe\"\n}",
                            "options": {
                                "raw": {
                                    "language": "json"
                                }
                            }
                        },
                        "url": {
                            "raw": "{{baseUrl}}/api/sign-up",
                            "host": [
                                "{{baseUrl}}"
                            ],
                            "path": [
                                "api",
                                "sign-up"
                            ]
                        }
                    },
                    "response": []
                },
                {
                    "name": "Sign In",
                    "request": {
                        "method": "POST",
                        "header": [],
                        "body": {
                            "mode": "raw",
                            "raw": "{\n  \"email\": \"user@example.com\",\n  \"password\": \"SecurePassword123!\"\n}",
                            "options": {
                                "raw": {
                                    "language": "json"
                                }
                            }
                        },
                        "url": {
                            "raw": "{{baseUrl}}/api/sign-in",
                            "host": [
                                "{{baseUrl}}"
                            ],
                            "path": [
                                "api",
                                "sign-in"
                            ]
                        }
                    },
                    "response": []
                },
                {
                    "name": "Get Session",
                    "request": {
                        "method": "GET",
                        "header": [],
                        "url": {
                            "raw": "{{baseUrl}}/api/session",
                            "host": [
                                "{{baseUrl}}"
                            ],
                            "path": [
                                "api",
                                "session"
                            ]
                        }
                    },
                    "response": []
                },
                {
                    "name": "Get Profile",
                    "request": {
                        "method": "GET",
                        "header": [],
                        "url": {
                            "raw": "{{baseUrl}}/api/profile",
                            "host": [
                                "{{baseUrl}}"
                            ],
                            "path": [
                                "api",
                                "profile"
                            ]
                        }
                    },
                    "response": []
                },
                {
                    "name": "Update Profile",
                    "request": {
                        "method": "PUT",
                        "header": [],
                        "body": {
                            "mode": "raw",
                            "raw": "{\n  \"name\": \"John Smith\"\n}",
                            "options": {
                                "raw": {
                                    "language": "json"
                                }
                            }
                        },
                        "url": {
                            "raw": "{{baseUrl}}/api/profile",
                            "host": [
                                "{{baseUrl}}"
                            ],
                            "path": [
                                "api",
                                "profile"
                            ]
                        }
                    },
                    "response": []
                },
                {
                    "name": "Sign Out",
                    "request": {
                        "method": "POST",
                        "header": [],
                        "url": {
                            "raw": "{{baseUrl}}/api/signout",
                            "host": [
                                "{{baseUrl}}"
                            ],
                            "path": [
                                "api",
                                "signout"
                            ]
                        }
                    },
                    "response": []
                }
            ]
        },
        {
            "name": "Password Reset",
            "item": [
                {
                    "name": "Request Reset",
                    "request": {
                        "method": "POST",
                        "header": [],
                        "body": {
                            "mode": "raw",
                            "raw": "{\n  \"email\": \"user@example.com\"\n}",
                            "options": {
                                "raw": {
                                    "language": "json"
                                }
                            }
                        },
                        "url": {
                            "raw": "{{baseUrl}}/api/auth/password-reset/request",
                            "host": [
                                "{{baseUrl}}"
                            ],
                            "path": [
                                "api",
                                "auth",
                                "password-reset",
                                "request"
                            ]
                        }
                    },
                    "response": []
                },
                {
                    "name": "Verify Token",
                    "request": {
                        "method": "POST",
                        "header": [],
                        "body": {
                            "mode": "raw",
                            "raw": "{\n  \"token\": \"your-token-here\"\n}",
                            "options": {
                                "raw": {
                                    "language": "json"
                                }
                            }
                        },
                        "url": {
                            "raw": "{{baseUrl}}/api/auth/password-reset/verify",
                            "host": [
                                "{{baseUrl}}"
                            ],
                            "path": [
                                "api",
                                "auth",
                                "password-reset",
                                "verify"
                            ]
                        }
                    },
                    "response": []
                },
                {
                    "name": "Reset Password",
                    "request": {
                        "method": "POST",
                        "header": [],
                        "body": {
                            "mode": "raw",
                            "raw": "{\n  \"token\": \"your-token-here\",\n  \"newPassword\": \"NewPassword123!\"\n}",
                            "options": {
                                "raw": {
                                    "language": "json"
                                }
                            }
                        },
                        "url": {
                            "raw": "{{baseUrl}}/api/auth/password-reset/reset",
                            "host": [
                                "{{baseUrl}}"
                            ],
                            "path": [
                                "api",
                                "auth",
                                "password-reset",
                                "reset"
                            ]
                        }
                    },
                    "response": []
                }
            ]
        },
        {
            "name": "Email Verification",
            "item": [
                {
                    "name": "Send Verification Email",
                    "request": {
                        "method": "POST",
                        "header": [],
                        "url": {
                            "raw": "{{baseUrl}}/api/auth/verify-email/send",
                            "host": [
                                "{{baseUrl}}"
                            ],
                            "path": [
                                "api",
                                "auth",
                                "verify-email",
                                "send"
                            ]
                        }
                    },
                    "response": []
                },
                {
                    "name": "Verify Email",
                    "request": {
                        "method": "POST",
                        "header": [],
                        "body": {
                            "mode": "raw",
                            "raw": "{\n  \"token\": \"your-token-here\"\n}",
                            "options": {
                                "raw": {
                                    "language": "json"
                                }
                            }
                        },
                        "url": {
                            "raw": "{{baseUrl}}/api/auth/verify-email",
                            "host": [
                                "{{baseUrl}}"
                            ],
                            "path": [
                                "api",
                                "auth",
                                "verify-email"
                            ]
                        }
                    },
                    "response": []
                }
            ]
        },
        {
            "name": "Session Management",
            "item": [
                {
                    "name": "List Sessions",
                    "request": {
                        "method": "GET",
                        "header": [],
                        "url": {
                            "raw": "{{baseUrl}}/api/sessions",
                            "host": [
                                "{{baseUrl}}"
                            ],
                            "path": [
                                "api",
                                "sessions"
                            ]
                        }
                    },
                    "response": []
                },
                {
                    "name": "Revoke Session",
                    "request": {
                        "method": "DELETE",
                        "header": [],
                        "url": {
                            "raw": "{{baseUrl}}/api/sessions/:sessionId",
                            "host": [
                                "{{baseUrl}}"
                            ],
                            "path": [
                                "api",
                                "sessions",
                                ":sessionId"
                            ],
                            "variable": [
                                {
                                    "key": "sessionId",
                                    "value": ""
                                }
                            ]
                        }
                    },
                    "response": []
                },
                {
                    "name": "Revoke All Sessions",
                    "request": {
                        "method": "DELETE",
                        "header": [],
                        "url": {
                            "raw": "{{baseUrl}}/api/sessions/all",
                            "host": [
                                "{{baseUrl}}"
                            ],
                            "path": [
                                "api",
                                "sessions",
                                "all"
                            ]
                        }
                    },
                    "response": []
                }
            ]
        },
        {
            "name": "Account Security",
            "item": [
                {
                    "name": "Change Password",
                    "request": {
                        "method": "POST",
                        "header": [],
                        "body": {
                            "mode": "raw",
                            "raw": "{\n  \"currentPassword\": \"OldPassword123!\",\n  \"newPassword\": \"NewPassword123!\"\n}",
                            "options": {
                                "raw": {
                                    "language": "json"
                                }
                            }
                        },
                        "url": {
                            "raw": "{{baseUrl}}/api/auth/change-password",
                            "host": [
                                "{{baseUrl}}"
                            ],
                            "path": [
                                "api",
                                "auth",
                                "change-password"
                            ]
                        }
                    },
                    "response": []
                },
                {
                    "name": "Delete Account",
                    "request": {
                        "method": "DELETE",
                        "header": [],
                        "body": {
                            "mode": "raw",
                            "raw": "{\n  \"password\": \"YourPassword123!\"\n}",
                            "options": {
                                "raw": {
                                    "language": "json"
                                }
                            }
                        },
                        "url": {
                            "raw": "{{baseUrl}}/api/auth/account",
                            "host": [
                                "{{baseUrl}}"
                            ],
                            "path": [
                                "api",
                                "auth",
                                "account"
                            ]
                        }
                    },
                    "response": []
                }
            ]
        },
        {
            "name": "Business Management",
            "item": [
                {
                    "name": "Create Business",
                    "request": {
                        "method": "POST",
                        "header": [],
                        "body": {
                            "mode": "raw",
                            "raw": "{\n  \"name\": \"My Pharmacy\",\n  \"address\": \"123 Main St, Mogadishu\",\n  \"phone\": \"+25212345678\"\n}",
                            "options": {
                                "raw": {
                                    "language": "json"
                                }
                            }
                        },
                        "url": {
                            "raw": "{{baseUrl}}/api/business",
                            "host": [
                                "{{baseUrl}}"
                            ],
                            "path": [
                                "api",
                                "business"
                            ]
                        }
                    },
                    "response": []
                },
                {
                    "name": "Get Business",
                    "request": {
                        "method": "GET",
                        "header": [],
                        "url": {
                            "raw": "{{baseUrl}}/api/business",
                            "host": [
                                "{{baseUrl}}"
                            ],
                            "path": [
                                "api",
                                "business"
                            ]
                        }
                    },
                    "response": []
                },
                {
                    "name": "Update Business",
                    "request": {
                        "method": "PUT",
                        "header": [],
                        "body": {
                            "mode": "raw",
                            "raw": "{\n  \"name\": \"Updated Pharmacy\"\n}",
                            "options": {
                                "raw": {
                                    "language": "json"
                                }
                            }
                        },
                        "url": {
                            "raw": "{{baseUrl}}/api/business",
                            "host": [
                                "{{baseUrl}}"
                            ],
                            "path": [
                                "api",
                                "business"
                            ]
                        }
                    },
                    "response": []
                }
            ]
        },
        {
            "name": "User Management",
            "item": [
                {
                    "name": "List Business Users",
                    "request": {
                        "method": "GET",
                        "header": [],
                        "url": {
                            "raw": "{{baseUrl}}/api/business/users",
                            "host": [
                                "{{baseUrl}}"
                            ],
                            "path": [
                                "api",
                                "business",
                                "users"
                            ]
                        }
                    },
                    "response": []
                },
                {
                    "name": "Update User Role",
                    "request": {
                        "method": "PUT",
                        "header": [],
                        "body": {
                            "mode": "raw",
                            "raw": "{\n  \"role\": \"OWNER\"\n}",
                            "options": {
                                "raw": {
                                    "language": "json"
                                }
                            }
                        },
                        "url": {
                            "raw": "{{baseUrl}}/api/business/users/:userId/role",
                            "host": [
                                "{{baseUrl}}"
                            ],
                            "path": [
                                "api",
                                "business",
                                "users",
                                ":userId",
                                "role"
                            ],
                            "variable": [
                                {
                                    "key": "userId",
                                    "value": ""
                                }
                            ]
                        }
                    },
                    "response": []
                },
                {
                    "name": "Remove User",
                    "request": {
                        "method": "DELETE",
                        "header": [],
                        "url": {
                            "raw": "{{baseUrl}}/api/business/users/:userId",
                            "host": [
                                "{{baseUrl}}"
                            ],
                            "path": [
                                "api",
                                "business",
                                "users",
                                ":userId"
                            ],
                            "variable": [
                                {
                                    "key": "userId",
                                    "value": ""
                                }
                            ]
                        }
                    },
                    "response": []
                }
            ]
        },
        {
            "name": "Staff Invitations",
            "item": [
                {
                    "name": "Invite Staff",
                    "request": {
                        "method": "POST",
                        "header": [],
                        "body": {
                            "mode": "raw",
                            "raw": "{\n  \"email\": \"staff@example.com\",\n  \"role\": \"STAFF\"\n}",
                            "options": {
                                "raw": {
                                    "language": "json"
                                }
                            }
                        },
                        "url": {
                            "raw": "{{baseUrl}}/api/business/invite",
                            "host": [
                                "{{baseUrl}}"
                            ],
                            "path": [
                                "api",
                                "business",
                                "invite"
                            ]
                        }
                    },
                    "response": []
                },
                {
                    "name": "Accept Invitation",
                    "request": {
                        "method": "POST",
                        "header": [],
                        "body": {
                            "mode": "raw",
                            "raw": "{\n  \"token\": \"invitation-token-here\"\n}",
                            "options": {
                                "raw": {
                                    "language": "json"
                                }
                            }
                        },
                        "url": {
                            "raw": "{{baseUrl}}/api/business/invite/accept",
                            "host": [
                                "{{baseUrl}}"
                            ],
                            "path": [
                                "api",
                                "business",
                                "invite",
                                "accept"
                            ]
                        }
                    },
                    "response": []
                },
                {
                    "name": "List Invitations",
                    "request": {
                        "method": "GET",
                        "header": [],
                        "url": {
                            "raw": "{{baseUrl}}/api/business/invitations",
                            "host": [
                                "{{baseUrl}}"
                            ],
                            "path": [
                                "api",
                                "business",
                                "invitations"
                            ]
                        }
                    },
                    "response": []
                },
                {
                    "name": "Revoke Invitation",
                    "request": {
                        "method": "DELETE",
                        "header": [],
                        "url": {
                            "raw": "{{baseUrl}}/api/business/invite/:id",
                            "host": [
                                "{{baseUrl}}"
                            ],
                            "path": [
                                "api",
                                "business",
                                "invite",
                                ":id"
                            ],
                            "variable": [
                                {
                                    "key": "id",
                                    "value": ""
                                }
                            ]
                        }
                    },
                    "response": []
                }
            ]
        },
        {
            "name": "Health Check",
            "request": {
                "method": "GET",
                "header": [],
                "url": {
                    "raw": "{{baseUrl}}/health",
                    "host": [
                        "{{baseUrl}}"
                    ],
                    "path": [
                        "health"
                    ]
                }
            },
            "response": []
        }
    ],
    "event": [
        {
            "listen": "prerequest",
            "script": {
                "type": "text/javascript",
                "exec": [
                    ""
                ]
            }
        },
        {
            "listen": "test",
            "script": {
                "type": "text/javascript",
                "exec": [
                    ""
                ]
            }
        }
    ],
    "variable": [
        {
            "key": "baseUrl",
            "value": "http://localhost:5000",
            "type": "string"
        }
    ]
}